sphinx_timeline/__init__.py
sphinx_timeline/dtime.py
sphinx_timeline/main.py
sphinx_timeline/static/__init__.py
sphinx_timeline/static/datetime.js
sphinx_timeline/static/default.css
sphinx_timeline-0.2.1.dist-info/LICENSE
sphinx_timeline-0.2.1.dist-info/WHEEL
sphinx_timeline-0.2.1.dist-info/METADATA
sphinx_timeline-0.2.1.dist-info/RECORD
